{
  "@openzeppelin/contracts@5.6.1/token/ERC20/IERC20.sol": ".deps/npm/@openzeppelin/contracts@5.6.1/token/ERC20/IERC20.sol",
  "@openzeppelin/contracts@5.6.1/token/ERC20/ERC20.sol": ".deps/npm/@openzeppelin/contracts@5.6.1/token/ERC20/ERC20.sol",
  "@openzeppelin/contracts@5.6.1/token/ERC20/extensions/IERC20Metadata.sol": ".deps/npm/@openzeppelin/contracts@5.6.1/token/ERC20/extensions/IERC20Metadata.sol",
  "@openzeppelin/contracts@5.6.1/utils/Context.sol": ".deps/npm/@openzeppelin/contracts@5.6.1/utils/Context.sol",
  "@openzeppelin/contracts@5.6.1/interfaces/draft-IERC6093.sol": ".deps/npm/@openzeppelin/contracts@5.6.1/interfaces/draft-IERC6093.sol",
  "@openzeppelin/contracts@5.6.1/toke/ERC20/IERC20.sol": ".deps/npm/@openzeppelin/contracts@5.6.1/toke/ERC20/IERC20.sol",
  "@openzeppelin/contracts@5.6.1/tok/ERC20/IERC20.sol": ".deps/npm/@openzeppelin/contracts@5.6.1/tok/ERC20/IERC20.sol",
  "@openzeppelin/contracts@5.6.1/to/ERC20/IERC20.sol": ".deps/npm/@openzeppelin/contracts@5.6.1/to/ERC20/IERC20.sol",
  "@openzeppelin/contracts@5.6.1/t/ERC20/IERC20.sol": ".deps/npm/@openzeppelin/contracts@5.6.1/t/ERC20/IERC20.sol",
  "@openzeppelin/contracts@5.6.1//ERC20/IERC20.sol": ".deps/npm/@openzeppelin/contracts@5.6.1//ERC20/IERC20.sol",
  "@openzeppelin/contracts@5.6.1/a/ERC20/IERC20.sol": ".deps/npm/@openzeppelin/contracts@5.6.1/a/ERC20/IERC20.sol",
  "@openzeppelin/contracts@5.6.1/ac/ERC20/IERC20.sol": ".deps/npm/@openzeppelin/contracts@5.6.1/ac/ERC20/IERC20.sol",
  "@openzeppelin/contracts@5.6.1/acc/ERC20/IERC20.sol": ".deps/npm/@openzeppelin/contracts@5.6.1/acc/ERC20/IERC20.sol",
  "@openzeppelin/contracts@5.6.1/acce/ERC20/IERC20.sol": ".deps/npm/@openzeppelin/contracts@5.6.1/acce/ERC20/IERC20.sol",
  "@openzeppelin/contracts@5.6.1/acces/ERC20/IERC20.sol": ".deps/npm/@openzeppelin/contracts@5.6.1/acces/ERC20/IERC20.sol",
  "@openzeppelin/contracts@5.6.1/access/ERC20/IERC20.sol": ".deps/npm/@openzeppelin/contracts@5.6.1/access/ERC20/IERC20.sol",
  "@openzeppelin/contracts@5.6.1/access/owable.sol": ".deps/npm/@openzeppelin/contracts@5.6.1/access/owable.sol",
  "@openzeppelin/contracts@5.6.1/access/owble.sol": ".deps/npm/@openzeppelin/contracts@5.6.1/access/owble.sol",
  "@openzeppelin/contracts@5.6.1/access/ownble.sol": ".deps/npm/@openzeppelin/contracts@5.6.1/access/ownble.sol",
  "@openzeppelin/contracts@5.6.1/access/ownable.sol": ".deps/npm/@openzeppelin/contracts@5.6.1/access/ownable.sol",
  "@openzeppelin/contracts@5.6.1/access/wnable.sol": ".deps/npm/@openzeppelin/contracts@5.6.1/access/wnable.sol",
  "@openzeppelin/contracts@5.6.1/access/Ownable.sol": ".deps/npm/@openzeppelin/contracts@5.6.1/access/Ownable.sol"
}